check_run.py
check_run-0.0.1.dist-info/LICENSE
check_run-0.0.1.dist-info/METADATA
check_run-0.0.1.dist-info/WHEEL
check_run-0.0.1.dist-info/top_level.txt
check_run-0.0.1.dist-info/RECORD
