Metadata-Version: 2.1
Name: check_run
Version: 0.0.1
Summary: check project is ran
Author-email: stone <stonepy01@gmail.com>
Classifier: Programming Language :: Python :: 3
Classifier: License :: OSI Approved :: MIT License
Classifier: Operating System :: OS Independent
Requires-Python: >=3.6
License-File: LICENSE
